[
    {
        "id": 1,
        "slotName": "Accessory",
        "name": "Trace Goggles Monday",
        "isBasic": true,
        "amount": 1,
        "slotId": 14
    },
    {
        "id": 2,
        "slotName": "Accessory",
        "name": "Trace Goggles Wednesday",
        "isBasic": true,
        "amount": 1,
        "slotId": 14
    },
    {
        "id": 3,
        "slotName": "Accessory",
        "name": "Trace Goggles Friday",
        "isBasic": false,
        "amount": 1,
        "slotId": 14
    },
    {
        "id": 4,
        "slotName": "Accessory",
        "name": "Trace Goggles Sunday",
        "isBasic": false,
        "amount": 1,
        "slotId": 14
    },
    {
        "id": 5,
        "slotName": "Accessory",
        "name": "Widowmaker Visor",
        "isBasic": false,
        "amount": 1,
        "slotId": 14
    },
    {
        "id": 6,
        "slotName": "Accessory",
        "name": "Brow Glasses Laurel",
        "isBasic": false,
        "amount": 1,
        "slotId": 14
    },
    {
        "id": 7,
        "slotName": "Accessory",
        "name": "Cruise Missile Aviators",
        "isBasic": false,
        "amount": 1,
        "slotId": 14
    },
    {
        "id": 8,
        "slotName": "Accessory",
        "name": "Lemon Spectacles",
        "isBasic": false,
        "amount": 1,
        "slotId": 14
    },
    {
        "id": 9,
        "slotName": "Accessory",
        "name": "Undeniable Visor",
        "isBasic": false,
        "amount": 1,
        "slotId": 14
    },
    {
        "id": 10,
        "slotName": "Accessory",
        "name": "Magnanimous Specs",
        "isBasic": false,
        "amount": 1,
        "slotId": 14
    },
    {
        "id": 11,
        "slotName": "Accessory",
        "name": "Paris Summer Shades",
        "isBasic": false,
        "amount": 1,
        "slotId": 14
    },
    {
        "id": 12,
        "slotName": "Accessory",
        "name": "Paris Winter Shades",
        "isBasic": false,
        "amount": 1,
        "slotId": 14
    },
    {
        "id": 13,
        "slotName": "Accessory",
        "name": "Paris Spring  Shades",
        "isBasic": false,
        "amount": 1,
        "slotId": 14
    },
    {
        "id": 14,
        "slotName": "Accessory",
        "name": "Paris Autumn Shades",
        "isBasic": false,
        "amount": 1,
        "slotId": 14
    },
    {
        "id": 15,
        "slotName": "Accessory",
        "name": "Travis Glasses",
        "isBasic": false,
        "amount": 1,
        "slotId": 14
    },
    {
        "id": 16,
        "slotName": "Accessory",
        "name": "Prescription Shades",
        "isBasic": false,
        "amount": 1,
        "slotId": 14
    },
    {
        "id": 17,
        "slotName": "Background",
        "name": "Skytower City (Base)",
        "isBasic": false,
        "amount": 1,
        "slotId": 8
    },
    {
        "id": 18,
        "slotName": "Background",
        "name": "Lunar Citadel (Base)",
        "isBasic": false,
        "amount": 1,
        "slotId": 8
    },
    {
        "id": 19,
        "slotName": "Background",
        "name": "Celestial Temple (Base)",
        "isBasic": true,
        "amount": 1,
        "slotId": 8
    },
    {
        "id": 20,
        "slotName": "Background",
        "name": "Astral Grotto (Base)",
        "isBasic": true,
        "amount": 1,
        "slotId": 8
    },
    {
        "id": 21,
        "slotName": "Background",
        "name": "Starlight Refuge (Base)",
        "isBasic": false,
        "amount": 1,
        "slotId": 8
    },
    {
        "id": 22,
        "slotName": "Background",
        "name": "Arcanum Outpost (Base)",
        "isBasic": false,
        "amount": 1,
        "slotId": 8
    },
    {
        "id": 23,
        "slotName": "Background",
        "name": "Azure Sky Port (Base)",
        "isBasic": false,
        "amount": 1,
        "slotId": 8
    },
    {
        "id": 24,
        "slotName": "Background",
        "name": "Echoes of Eternity (Base)",
        "isBasic": false,
        "amount": 1,
        "slotId": 8
    },
    {
        "id": 25,
        "slotName": "Background",
        "name": "Crystalhaven Sanctuary (Base)",
        "isBasic": false,
        "amount": 1,
        "slotId": 8
    },
    {
        "id": 26,
        "slotName": "Background",
        "name": "Eldertree Grove (Base)",
        "isBasic": false,
        "amount": 1,
        "slotId": 8
    },
    {
        "id": 27,
        "slotName": "Background",
        "name": "Dragonfire Canyon (Base)",
        "isBasic": false,
        "amount": 1,
        "slotId": 8
    },
    {
        "id": 28,
        "slotName": "Background",
        "name": "Shimmering Isles (Base)",
        "isBasic": false,
        "amount": 1,
        "slotId": 8
    },
    {
        "id": 29,
        "slotName": "Background",
        "name": "Elemental Glade (Base)",
        "isBasic": false,
        "amount": 1,
        "slotId": 8
    },
    {
        "id": 30,
        "slotName": "Background",
        "name": "Starfall Keep (Base)",
        "isBasic": false,
        "amount": 1,
        "slotId": 8
    },
    {
        "id": 31,
        "slotName": "Background",
        "name": "Shadowvale Woods (Base)",
        "isBasic": false,
        "amount": 1,
        "slotId": 8
    },
    {
        "id": 32,
        "slotName": "Background",
        "name": "Thunderhead Peak (Base)",
        "isBasic": false,
        "amount": 1,
        "slotId": 8
    },
    {
        "id": 33,
        "slotName": "Background",
        "name": "Starlight Village (Base)",
        "isBasic": false,
        "amount": 1,
        "slotId": 8
    },
    {
        "id": 34,
        "slotName": "Background",
        "name": "Solaria Kingdom (Base)",
        "isBasic": false,
        "amount": 1,
        "slotId": 8
    },
    {
        "id": 35,
        "slotName": "Background",
        "name": "Nexus Bastion (Base)",
        "isBasic": false,
        "amount": 1,
        "slotId": 8
    },
    {
        "id": 36,
        "slotName": "Background",
        "name": "Stormwarden Stronghold (Base)",
        "isBasic": false,
        "amount": 1,
        "slotId": 8
    },
    {
        "id": 37,
        "slotName": "Background",
        "name": "Gravity Rift Fortress (Base)",
        "isBasic": false,
        "amount": 1,
        "slotId": 8
    },
    {
        "id": 38,
        "slotName": "Background",
        "name": "Voidgate Tower (Base)",
        "isBasic": false,
        "amount": 1,
        "slotId": 8
    },
    {
        "id": 39,
        "slotName": "Background",
        "name": "Poseidon's Rest (Base)",
        "isBasic": false,
        "amount": 1,
        "slotId": 8
    },
    {
        "id": 40,
        "slotName": "Background",
        "name": "Raptor's Aerie (Base)",
        "isBasic": false,
        "amount": 1,
        "slotId": 8
    },
    {
        "id": 41,
        "slotName": "Background",
        "name": "Taufik's Last Stand (Base)",
        "isBasic": false,
        "amount": 1,
        "slotId": 8
    },
    {
        "id": 42,
        "slotName": "Background",
        "name": "Eldritch Marsh (Base)",
        "isBasic": false,
        "amount": 1,
        "slotId": 8
    },
    {
        "id": 43,
        "slotName": "Background",
        "name": "Knowhere (Base)",
        "isBasic": false,
        "amount": 1,
        "slotId": 8
    },
    {
        "id": 44,
        "slotName": "Background",
        "name": "Skullcrusher Mountain (Base)",
        "isBasic": false,
        "amount": 1,
        "slotId": 8
    },
    {
        "id": 45,
        "slotName": "Background",
        "name": "The Infinite Ocean (Base)",
        "isBasic": false,
        "amount": 1,
        "slotId": 8
    },
    {
        "id": 46,
        "slotName": "Bottom",
        "name": "Diana Leggings",
        "isBasic": false,
        "amount": 1,
        "slotId": 12
    },
    {
        "id": 47,
        "slotName": "Bottom",
        "name": "Coman Leggings",
        "isBasic": false,
        "amount": 1,
        "slotId": 12
    },
    {
        "id": 48,
        "slotName": "Bottom",
        "name": "Matrix Leggings",
        "isBasic": false,
        "amount": 1,
        "slotId": 12
    },
    {
        "id": 49,
        "slotName": "Bottom",
        "name": "Levi Leggings",
        "isBasic": false,
        "amount": 1,
        "slotId": 12
    },
    {
        "id": 50,
        "slotName": "Bottom",
        "name": "Bloody Raiments",
        "isBasic": false,
        "amount": 1,
        "slotId": 12
    },
    {
        "id": 51,
        "slotName": "Bottom",
        "name": "Commander Leggings",
        "isBasic": false,
        "amount": 1,
        "slotId": 12
    },
    {
        "id": 52,
        "slotName": "Bottom",
        "name": "Teal Underwear",
        "isBasic": false,
        "amount": 1,
        "slotId": 12
    },
    {
        "id": 53,
        "slotName": "Bottom",
        "name": "Teal Boxers",
        "isBasic": false,
        "amount": 1,
        "slotId": 12
    },
    {
        "id": 54,
        "slotName": "Bottom",
        "name": "Tighty Tealies",
        "isBasic": false,
        "amount": 1,
        "slotId": 12
    },
    {
        "id": 55,
        "slotName": "Bottom",
        "name": "Corporal Leggings",
        "isBasic": false,
        "amount": 1,
        "slotId": 12
    },
    {
        "id": 56,
        "slotName": "Bottom",
        "name": "Galactic Leggings",
        "isBasic": false,
        "amount": 1,
        "slotId": 12
    },
    {
        "id": 57,
        "slotName": "Bottom",
        "name": "Forgotmy Leggings",
        "isBasic": false,
        "amount": 1,
        "slotId": 12
    },
    {
        "id": 58,
        "slotName": "Bottom",
        "name": "Guileless Leggings",
        "isBasic": false,
        "amount": 1,
        "slotId": 12
    },
    {
        "id": 59,
        "slotName": "Bottom",
        "name": "Natalya Pocket Legs",
        "isBasic": false,
        "amount": 1,
        "slotId": 12
    },
    {
        "id": 60,
        "slotName": "Bottom",
        "name": "Galahad Leggings",
        "isBasic": false,
        "amount": 1,
        "slotId": 12
    },
    {
        "id": 61,
        "slotName": "Bottom",
        "name": "Shadow Runner Legs",
        "isBasic": false,
        "amount": 1,
        "slotId": 12
    },
    {
        "id": 62,
        "slotName": "Bottom",
        "name": "Hermione Raiments",
        "isBasic": false,
        "amount": 1,
        "slotId": 12
    },
    {
        "id": 63,
        "slotName": "Bottom",
        "name": "Labyrinth Leggings",
        "isBasic": false,
        "amount": 1,
        "slotId": 12
    },
    {
        "id": 64,
        "slotName": "Bottom",
        "name": "Jag Leggings",
        "isBasic": false,
        "amount": 1,
        "slotId": 12
    },
    {
        "id": 65,
        "slotName": "Bottom",
        "name": "Tiamat Leggings",
        "isBasic": false,
        "amount": 1,
        "slotId": 12
    },
    {
        "id": 66,
        "slotName": "Bottom",
        "name": "Adams Leggings",
        "isBasic": false,
        "amount": 1,
        "slotId": 12
    },
    {
        "id": 67,
        "slotName": "Bottom",
        "name": "Canary Leggings",
        "isBasic": false,
        "amount": 1,
        "slotId": 12
    },
    {
        "id": 68,
        "slotName": "Bottom",
        "name": "Bond Leggings",
        "isBasic": false,
        "amount": 1,
        "slotId": 12
    },
    {
        "id": 69,
        "slotName": "Bottom",
        "name": "Midas Leggings",
        "isBasic": false,
        "amount": 1,
        "slotId": 12
    },
    {
        "id": 70,
        "slotName": "Bottom",
        "name": "Hannibal Leggings",
        "isBasic": false,
        "amount": 1,
        "slotId": 12
    },
    {
        "id": 71,
        "slotName": "Bottom",
        "name": "Green Underwear",
        "isBasic": false,
        "amount": 1,
        "slotId": 12
    },
    {
        "id": 72,
        "slotName": "Bottom",
        "name": "Green Boxers",
        "isBasic": false,
        "amount": 1,
        "slotId": 12
    },
    {
        "id": 73,
        "slotName": "Bottom",
        "name": "Strider Leggings",
        "isBasic": false,
        "amount": 1,
        "slotId": 12
    },
    {
        "id": 74,
        "slotName": "Bottom",
        "name": "Blitzkrieg Leggings",
        "isBasic": false,
        "amount": 1,
        "slotId": 12
    },
    {
        "id": 75,
        "slotName": "Bottom",
        "name": "Tighty Greenies",
        "isBasic": false,
        "amount": 1,
        "slotId": 12
    },
    {
        "id": 76,
        "slotName": "Bottom",
        "name": "Ranger Leggings",
        "isBasic": false,
        "amount": 1,
        "slotId": 12
    },
    {
        "id": 77,
        "slotName": "Bottom",
        "name": "Streetpop Leggings",
        "isBasic": false,
        "amount": 1,
        "slotId": 12
    },
    {
        "id": 78,
        "slotName": "Bottom",
        "name": "Necromantic Leggings",
        "isBasic": true,
        "amount": 1,
        "slotId": 12
    },
    {
        "id": 79,
        "slotName": "Bottom",
        "name": "Bleached Leggings",
        "isBasic": true,
        "amount": 1,
        "slotId": 12
    },
    {
        "id": 80,
        "slotName": "Bottom",
        "name": "Bladed Leggings",
        "isBasic": false,
        "amount": 1,
        "slotId": 12
    },
    {
        "id": 81,
        "slotName": "Bottom",
        "name": "Craft Leggings",
        "isBasic": false,
        "amount": 1,
        "slotId": 12
    },
    {
        "id": 82,
        "slotName": "Bottom",
        "name": "Ayane Leggings",
        "isBasic": false,
        "amount": 1,
        "slotId": 12
    },
    {
        "id": 83,
        "slotName": "Bottom",
        "name": "Arthur Leggings",
        "isBasic": false,
        "amount": 1,
        "slotId": 12
    },
    {
        "id": 84,
        "slotName": "Bottom",
        "name": "Kunoichi Leggings",
        "isBasic": false,
        "amount": 1,
        "slotId": 12
    },
    {
        "id": 85,
        "slotName": "Bottom",
        "name": "Archlich Leggings",
        "isBasic": false,
        "amount": 1,
        "slotId": 12
    },
    {
        "id": 86,
        "slotName": "Bottom",
        "name": "Spartan Leggings",
        "isBasic": false,
        "amount": 1,
        "slotId": 12
    },
    {
        "id": 87,
        "slotName": "Bottom",
        "name": "Techxpert Leggings",
        "isBasic": false,
        "amount": 1,
        "slotId": 12
    },
    {
        "id": 88,
        "slotName": "Bottom",
        "name": "Power Suit Leggings",
        "isBasic": false,
        "amount": 1,
        "slotId": 12
    },
    {
        "id": 89,
        "slotName": "Bottom",
        "name": "Midnight Leggings",
        "isBasic": false,
        "amount": 1,
        "slotId": 12
    },
    {
        "id": 90,
        "slotName": "Bottom",
        "name": "Resistance Leggings",
        "isBasic": false,
        "amount": 1,
        "slotId": 12
    },
    {
        "id": 91,
        "slotName": "Bottom",
        "name": "Shinobi Leggings",
        "isBasic": false,
        "amount": 1,
        "slotId": 12
    },
    {
        "id": 92,
        "slotName": "Bottom",
        "name": "Citrus Leggings",
        "isBasic": false,
        "amount": 1,
        "slotId": 12
    },
    {
        "id": 93,
        "slotName": "Bottom",
        "name": "Orange Underwear",
        "isBasic": false,
        "amount": 1,
        "slotId": 12
    },
    {
        "id": 94,
        "slotName": "Bottom",
        "name": "Orange Boxers",
        "isBasic": false,
        "amount": 1,
        "slotId": 12
    },
    {
        "id": 95,
        "slotName": "Bottom",
        "name": "Tighty Orangies",
        "isBasic": false,
        "amount": 1,
        "slotId": 12
    },
    {
        "id": 96,
        "slotName": "Bottom",
        "name": "Mandarin Leggings",
        "isBasic": false,
        "amount": 1,
        "slotId": 12
    },
    {
        "id": 97,
        "slotName": "Bottom",
        "name": "Pink Underwear",
        "isBasic": false,
        "amount": 1,
        "slotId": 12
    },
    {
        "id": 98,
        "slotName": "Bottom",
        "name": "Pink Boxers",
        "isBasic": false,
        "amount": 1,
        "slotId": 12
    },
    {
        "id": 99,
        "slotName": "Bottom",
        "name": "Tighty Pinkies",
        "isBasic": false,
        "amount": 1,
        "slotId": 12
    },
    {
        "id": 100,
        "slotName": "Bottom",
        "name": "Consecrated Leggings",
        "isBasic": false,
        "amount": 1,
        "slotId": 12
    },
    {
        "id": 101,
        "slotName": "Bottom",
        "name": "Divine Leggings",
        "isBasic": false,
        "amount": 1,
        "slotId": 12
    },
    {
        "id": 102,
        "slotName": "Bottom",
        "name": "Strange Leggings",
        "isBasic": false,
        "amount": 1,
        "slotId": 12
    },
    {
        "id": 103,
        "slotName": "Bottom",
        "name": "Sniper Leggings",
        "isBasic": false,
        "amount": 1,
        "slotId": 12
    },
    {
        "id": 104,
        "slotName": "Bottom",
        "name": "Bloodshot Leggings",
        "isBasic": false,
        "amount": 1,
        "slotId": 12
    },
    {
        "id": 105,
        "slotName": "Bottom",
        "name": "Red Underwear",
        "isBasic": false,
        "amount": 1,
        "slotId": 12
    },
    {
        "id": 106,
        "slotName": "Bottom",
        "name": "Red Boxers",
        "isBasic": false,
        "amount": 1,
        "slotId": 12
    },
    {
        "id": 107,
        "slotName": "Bottom",
        "name": "Nokizaru Leggings",
        "isBasic": false,
        "amount": 1,
        "slotId": 12
    },
    {
        "id": 108,
        "slotName": "Bottom",
        "name": "Tighty Reddies",
        "isBasic": false,
        "amount": 1,
        "slotId": 12
    },
    {
        "id": 109,
        "slotName": "Bottom",
        "name": "Crimson Leggings",
        "isBasic": false,
        "amount": 1,
        "slotId": 12
    },
    {
        "id": 110,
        "slotName": "Bottom",
        "name": "Yoroi Leggings",
        "isBasic": false,
        "amount": 1,
        "slotId": 12
    },
    {
        "id": 111,
        "slotName": "Bottom",
        "name": "Assault Leggings",
        "isBasic": false,
        "amount": 1,
        "slotId": 12
    },
    {
        "id": 112,
        "slotName": "Bottom",
        "name": "Crusader Leggings",
        "isBasic": false,
        "amount": 1,
        "slotId": 12
    },
    {
        "id": 113,
        "slotName": "Bottom",
        "name": "Recruit Leggings",
        "isBasic": false,
        "amount": 1,
        "slotId": 12
    },
    {
        "id": 114,
        "slotName": "Bottom",
        "name": "Otaku Leggings",
        "isBasic": false,
        "amount": 1,
        "slotId": 12
    },
    {
        "id": 115,
        "slotName": "Bottom",
        "name": "Angel Leggings",
        "isBasic": false,
        "amount": 1,
        "slotId": 12
    },
    {
        "id": 116,
        "slotName": "Bottom",
        "name": "Slayer Leggings",
        "isBasic": false,
        "amount": 1,
        "slotId": 12
    },
    {
        "id": 117,
        "slotName": "Bottom",
        "name": "Celestial Leggings",
        "isBasic": true,
        "amount": 1,
        "slotId": 12
    },
    {
        "id": 118,
        "slotName": "Eyes",
        "name": "Anger",
        "isBasic": true,
        "amount": 1,
        "slotId": 2
    },
    {
        "id": 119,
        "slotName": "Eyes",
        "name": "Bushy",
        "isBasic": false,
        "amount": 1,
        "slotId": 2
    },
    {
        "id": 120,
        "slotName": "Eyes",
        "name": "Patch",
        "isBasic": false,
        "amount": 1,
        "slotId": 2
    },
    {
        "id": 121,
        "slotName": "Eyes",
        "name": "Fire",
        "isBasic": false,
        "amount": 1,
        "slotId": 2
    },
    {
        "id": 122,
        "slotName": "Eyes",
        "name": "Happy",
        "isBasic": false,
        "amount": 1,
        "slotId": 2
    },
    {
        "id": 123,
        "slotName": "Eyes",
        "name": "Ice",
        "isBasic": false,
        "amount": 1,
        "slotId": 2
    },
    {
        "id": 124,
        "slotName": "Eyes",
        "name": "Mischief",
        "isBasic": false,
        "amount": 1,
        "slotId": 2
    },
    {
        "id": 125,
        "slotName": "Eyes",
        "name": "Original",
        "isBasic": false,
        "amount": 1,
        "slotId": 2
    },
    {
        "id": 126,
        "slotName": "Eyes",
        "name": "Poison",
        "isBasic": false,
        "amount": 1,
        "slotId": 2
    },
    {
        "id": 127,
        "slotName": "Eyes",
        "name": "Scar",
        "isBasic": false,
        "amount": 1,
        "slotId": 2
    },
    {
        "id": 128,
        "slotName": "Eyes",
        "name": "Shellshock",
        "isBasic": false,
        "amount": 1,
        "slotId": 2
    },
    {
        "id": 129,
        "slotName": "Eyes",
        "name": "Sneaky",
        "isBasic": false,
        "amount": 1,
        "slotId": 2
    },
    {
        "id": 130,
        "slotName": "Eyes",
        "name": "uwu",
        "isBasic": false,
        "amount": 1,
        "slotId": 2
    },
    {
        "id": 131,
        "slotName": "Eyes",
        "name": "Wink",
        "isBasic": false,
        "amount": 1,
        "slotId": 2
    },
    {
        "id": 132,
        "slotName": "Eyes",
        "name": "Kabuki",
        "isBasic": false,
        "amount": 1,
        "slotId": 2
    },
    {
        "id": 133,
        "slotName": "Eyes",
        "name": "Anger",
        "isBasic": false,
        "amount": 1,
        "slotId": 2
    },
    {
        "id": 134,
        "slotName": "Eyes",
        "name": "Bright",
        "isBasic": false,
        "amount": 1,
        "slotId": 2
    },
    {
        "id": 135,
        "slotName": "Eyes",
        "name": "Bushy",
        "isBasic": false,
        "amount": 1,
        "slotId": 2
    },
    {
        "id": 136,
        "slotName": "Eyes",
        "name": "Fire",
        "isBasic": false,
        "amount": 1,
        "slotId": 2
    },
    {
        "id": 137,
        "slotName": "Eyes",
        "name": "Happy",
        "isBasic": false,
        "amount": 1,
        "slotId": 2
    },
    {
        "id": 138,
        "slotName": "Eyes",
        "name": "Ice",
        "isBasic": false,
        "amount": 1,
        "slotId": 2
    },
    {
        "id": 139,
        "slotName": "Eyes",
        "name": "Poison",
        "isBasic": false,
        "amount": 1,
        "slotId": 2
    },
    {
        "id": 140,
        "slotName": "Eyes",
        "name": "Shellshock",
        "isBasic": false,
        "amount": 1,
        "slotId": 2
    },
    {
        "id": 141,
        "slotName": "Eyes",
        "name": "Sneaky",
        "isBasic": false,
        "amount": 1,
        "slotId": 2
    },
    {
        "id": 142,
        "slotName": "Hairstyle",
        "name": "Bald",
        "isBasic": false,
        "amount": 1,
        "slotId": 7
    },
    {
        "id": 143,
        "slotName": "Hairstyle",
        "name": "Blonde",
        "isBasic": false,
        "amount": 1,
        "slotId": 7
    },
    {
        "id": 144,
        "slotName": "Hairstyle",
        "name": "Dirty Blonde",
        "isBasic": false,
        "amount": 1,
        "slotId": 7
    },
    {
        "id": 145,
        "slotName": "Hairstyle",
        "name": "Black Pony",
        "isBasic": false,
        "amount": 1,
        "slotId": 7
    },
    {
        "id": 146,
        "slotName": "Hairstyle",
        "name": "Blonde Bun",
        "isBasic": false,
        "amount": 1,
        "slotId": 7
    },
    {
        "id": 147,
        "slotName": "Hairstyle",
        "name": "Blonde Buzzcut",
        "isBasic": false,
        "amount": 1,
        "slotId": 7
    },
    {
        "id": 148,
        "slotName": "Hairstyle",
        "name": "Short Pony",
        "isBasic": false,
        "amount": 1,
        "slotId": 7
    },
    {
        "id": 149,
        "slotName": "Hairstyle",
        "name": "Blue Bob",
        "isBasic": false,
        "amount": 1,
        "slotId": 7
    },
    {
        "id": 150,
        "slotName": "Hairstyle",
        "name": "Brawler Cut",
        "isBasic": false,
        "amount": 1,
        "slotId": 7
    },
    {
        "id": 151,
        "slotName": "Hairstyle",
        "name": "Brunette Cascade",
        "isBasic": false,
        "amount": 1,
        "slotId": 7
    },
    {
        "id": 152,
        "slotName": "Hairstyle",
        "name": "Brunette Pony",
        "isBasic": false,
        "amount": 1,
        "slotId": 7
    },
    {
        "id": 153,
        "slotName": "Hairstyle",
        "name": "Brunette Tied",
        "isBasic": false,
        "amount": 1,
        "slotId": 7
    },
    {
        "id": 154,
        "slotName": "Hairstyle",
        "name": "Buzzcut Buzzcut",
        "isBasic": false,
        "amount": 1,
        "slotId": 7
    },
    {
        "id": 155,
        "slotName": "Hairstyle",
        "name": "Frizzy",
        "isBasic": false,
        "amount": 1,
        "slotId": 7
    },
    {
        "id": 156,
        "slotName": "Hairstyle",
        "name": "Fonz",
        "isBasic": false,
        "amount": 1,
        "slotId": 7
    },
    {
        "id": 157,
        "slotName": "Hairstyle",
        "name": "Mohawk",
        "isBasic": false,
        "amount": 1,
        "slotId": 7
    },
    {
        "id": 158,
        "slotName": "Hairstyle",
        "name": "Elf",
        "isBasic": false,
        "amount": 1,
        "slotId": 7
    },
    {
        "id": 159,
        "slotName": "Hairstyle",
        "name": "Green Pony",
        "isBasic": false,
        "amount": 1,
        "slotId": 7
    },
    {
        "id": 160,
        "slotName": "Hairstyle",
        "name": "High Pony",
        "isBasic": false,
        "amount": 1,
        "slotId": 7
    },
    {
        "id": 161,
        "slotName": "Hairstyle",
        "name": "Kabuki Coiffe",
        "isBasic": true,
        "amount": 1,
        "slotId": 7
    },
    {
        "id": 162,
        "slotName": "Hairstyle",
        "name": "Long Blonde",
        "isBasic": true,
        "amount": 1,
        "slotId": 7
    },
    {
        "id": 163,
        "slotName": "Hairstyle",
        "name": "Light Blonde",
        "isBasic": false,
        "amount": 1,
        "slotId": 7
    },
    {
        "id": 164,
        "slotName": "Hairstyle",
        "name": "Brown Rat Tail",
        "isBasic": false,
        "amount": 1,
        "slotId": 7
    },
    {
        "id": 165,
        "slotName": "Hairstyle",
        "name": "Messy",
        "isBasic": false,
        "amount": 1,
        "slotId": 7
    },
    {
        "id": 166,
        "slotName": "Hairstyle",
        "name": "Decker Mohawk",
        "isBasic": false,
        "amount": 1,
        "slotId": 7
    },
    {
        "id": 167,
        "slotName": "Hairstyle",
        "name": "Green Long",
        "isBasic": false,
        "amount": 1,
        "slotId": 7
    },
    {
        "id": 168,
        "slotName": "Hairstyle",
        "name": "Green Short",
        "isBasic": false,
        "amount": 1,
        "slotId": 7
    },
    {
        "id": 169,
        "slotName": "Hairstyle",
        "name": "Super Dragon",
        "isBasic": false,
        "amount": 1,
        "slotId": 7
    },
    {
        "id": 170,
        "slotName": "Hairstyle",
        "name": "Protag",
        "isBasic": false,
        "amount": 1,
        "slotId": 7
    },
    {
        "id": 171,
        "slotName": "Hairstyle",
        "name": "Raider",
        "isBasic": false,
        "amount": 1,
        "slotId": 7
    },
    {
        "id": 172,
        "slotName": "Hairstyle",
        "name": "Black Rat Tail",
        "isBasic": false,
        "amount": 1,
        "slotId": 7
    },
    {
        "id": 173,
        "slotName": "Hairstyle",
        "name": "Red Cascade",
        "isBasic": false,
        "amount": 1,
        "slotId": 7
    },
    {
        "id": 174,
        "slotName": "Hairstyle",
        "name": "Red Pony",
        "isBasic": false,
        "amount": 1,
        "slotId": 7
    },
    {
        "id": 175,
        "slotName": "Hairstyle",
        "name": "Sakura",
        "isBasic": false,
        "amount": 1,
        "slotId": 7
    },
    {
        "id": 176,
        "slotName": "Hairstyle",
        "name": "Scorpion",
        "isBasic": false,
        "amount": 1,
        "slotId": 7
    },
    {
        "id": 177,
        "slotName": "Hairstyle",
        "name": "Short White",
        "isBasic": false,
        "amount": 1,
        "slotId": 7
    },
    {
        "id": 178,
        "slotName": "Hairstyle",
        "name": "Strawberry",
        "isBasic": false,
        "amount": 1,
        "slotId": 7
    },
    {
        "id": 179,
        "slotName": "Hairstyle",
        "name": "Raider",
        "isBasic": false,
        "amount": 1,
        "slotId": 7
    },
    {
        "id": 180,
        "slotName": "Hairstyle",
        "name": "Travis",
        "isBasic": false,
        "amount": 1,
        "slotId": 7
    },
    {
        "id": 181,
        "slotName": "Hairstyle",
        "name": "Undercroft",
        "isBasic": false,
        "amount": 1,
        "slotId": 7
    },
    {
        "id": 182,
        "slotName": "Hairstyle",
        "name": "Wanderer",
        "isBasic": false,
        "amount": 1,
        "slotId": 7
    },
    {
        "id": 183,
        "slotName": "Hairstyle",
        "name": "Long Elf White",
        "isBasic": false,
        "amount": 1,
        "slotId": 7
    },
    {
        "id": 184,
        "slotName": "Hairstyle",
        "name": "Wild",
        "isBasic": false,
        "amount": 1,
        "slotId": 7
    },
    {
        "id": 185,
        "slotName": "Headgear",
        "name": "Cyberjack Headset",
        "isBasic": false,
        "amount": 1,
        "slotId": 9
    },
    {
        "id": 186,
        "slotName": "Headgear",
        "name": "Red Bandana",
        "isBasic": false,
        "amount": 1,
        "slotId": 9
    },
    {
        "id": 187,
        "slotName": "Headgear",
        "name": "Bandana Bangle",
        "isBasic": false,
        "amount": 1,
        "slotId": 9
    },
    {
        "id": 188,
        "slotName": "Headgear",
        "name": "Beetle Helmet",
        "isBasic": false,
        "amount": 1,
        "slotId": 9
    },
    {
        "id": 189,
        "slotName": "Headgear",
        "name": "Red Headband",
        "isBasic": false,
        "amount": 1,
        "slotId": 9
    },
    {
        "id": 190,
        "slotName": "Headgear",
        "name": "Black Headband",
        "isBasic": false,
        "amount": 1,
        "slotId": 9
    },
    {
        "id": 191,
        "slotName": "Headgear",
        "name": "Black Hoodie",
        "isBasic": false,
        "amount": 1,
        "slotId": 9
    },
    {
        "id": 192,
        "slotName": "Headgear",
        "name": "Bomber Helm",
        "isBasic": false,
        "amount": 1,
        "slotId": 9
    },
    {
        "id": 193,
        "slotName": "Headgear",
        "name": "Brawler Black Bandana",
        "isBasic": false,
        "amount": 1,
        "slotId": 9
    },
    {
        "id": 194,
        "slotName": "Headgear",
        "name": "Brawler Blue Bandana",
        "isBasic": false,
        "amount": 1,
        "slotId": 9
    },
    {
        "id": 195,
        "slotName": "Headgear",
        "name": "Brawler Red Bandana",
        "isBasic": false,
        "amount": 1,
        "slotId": 9
    },
    {
        "id": 196,
        "slotName": "Headgear",
        "name": "Brown Bandana",
        "isBasic": false,
        "amount": 1,
        "slotId": 9
    },
    {
        "id": 197,
        "slotName": "Headgear",
        "name": "Neko Ears",
        "isBasic": false,
        "amount": 1,
        "slotId": 9
    },
    {
        "id": 198,
        "slotName": "Headgear",
        "name": "Neko Headset",
        "isBasic": false,
        "amount": 1,
        "slotId": 9
    },
    {
        "id": 199,
        "slotName": "Headgear",
        "name": "Red Cap",
        "isBasic": false,
        "amount": 1,
        "slotId": 9
    },
    {
        "id": 200,
        "slotName": "Headgear",
        "name": "Centurion Helm",
        "isBasic": false,
        "amount": 1,
        "slotId": 9
    },
    {
        "id": 201,
        "slotName": "Headgear",
        "name": "Dark Knight Helm",
        "isBasic": false,
        "amount": 1,
        "slotId": 9
    },
    {
        "id": 202,
        "slotName": "Headgear",
        "name": "Gray Hood",
        "isBasic": false,
        "amount": 1,
        "slotId": 9
    },
    {
        "id": 203,
        "slotName": "Headgear",
        "name": "Green Bandana",
        "isBasic": false,
        "amount": 1,
        "slotId": 9
    },
    {
        "id": 204,
        "slotName": "Headgear",
        "name": "Green Hood",
        "isBasic": false,
        "amount": 1,
        "slotId": 9
    },
    {
        "id": 205,
        "slotName": "Headgear",
        "name": "Green Hoodie",
        "isBasic": false,
        "amount": 1,
        "slotId": 9
    },
    {
        "id": 206,
        "slotName": "Headgear",
        "name": "Standard Headset",
        "isBasic": false,
        "amount": 1,
        "slotId": 9
    },
    {
        "id": 207,
        "slotName": "Headgear",
        "name": "Plumed Helm",
        "isBasic": true,
        "amount": 1,
        "slotId": 9
    },
    {
        "id": 208,
        "slotName": "Headgear",
        "name": "Horned Helm",
        "isBasic": true,
        "amount": 1,
        "slotId": 9
    },
    {
        "id": 209,
        "slotName": "Headgear",
        "name": "Hat of Wealth and Respect",
        "isBasic": false,
        "amount": 1,
        "slotId": 9
    },
    {
        "id": 210,
        "slotName": "Headgear",
        "name": "Hollow Mask",
        "isBasic": false,
        "amount": 1,
        "slotId": 9
    },
    {
        "id": 211,
        "slotName": "Headgear",
        "name": "Honor Helm",
        "isBasic": false,
        "amount": 1,
        "slotId": 9
    },
    {
        "id": 212,
        "slotName": "Headgear",
        "name": "Noble Helm",
        "isBasic": false,
        "amount": 1,
        "slotId": 9
    },
    {
        "id": 213,
        "slotName": "Headgear",
        "name": "Law Helm",
        "isBasic": false,
        "amount": 1,
        "slotId": 9
    },
    {
        "id": 214,
        "slotName": "Headgear",
        "name": "Hulk Bandana",
        "isBasic": false,
        "amount": 1,
        "slotId": 9
    },
    {
        "id": 215,
        "slotName": "Headgear",
        "name": "Flaming Skull Helm",
        "isBasic": false,
        "amount": 1,
        "slotId": 9
    },
    {
        "id": 216,
        "slotName": "Headgear",
        "name": "Long Red Bandana",
        "isBasic": false,
        "amount": 1,
        "slotId": 9
    },
    {
        "id": 217,
        "slotName": "Headgear",
        "name": "Closed Helm",
        "isBasic": false,
        "amount": 1,
        "slotId": 9
    },
    {
        "id": 218,
        "slotName": "Headgear",
        "name": "Meteor Helm",
        "isBasic": false,
        "amount": 1,
        "slotId": 9
    },
    {
        "id": 219,
        "slotName": "Headgear",
        "name": "Ninja Mask",
        "isBasic": false,
        "amount": 1,
        "slotId": 9
    },
    {
        "id": 220,
        "slotName": "Headgear",
        "name": "Oni Mask",
        "isBasic": false,
        "amount": 1,
        "slotId": 9
    },
    {
        "id": 221,
        "slotName": "Headgear",
        "name": "Pink Neko Headset",
        "isBasic": false,
        "amount": 1,
        "slotId": 9
    },
    {
        "id": 222,
        "slotName": "Headgear",
        "name": "Purple Hood",
        "isBasic": false,
        "amount": 1,
        "slotId": 9
    },
    {
        "id": 223,
        "slotName": "Headgear",
        "name": "Samurai Helm",
        "isBasic": false,
        "amount": 1,
        "slotId": 9
    },
    {
        "id": 224,
        "slotName": "Headgear",
        "name": "Cybernetic Helm",
        "isBasic": false,
        "amount": 1,
        "slotId": 9
    },
    {
        "id": 225,
        "slotName": "Headgear",
        "name": "Grinning Skull Helm",
        "isBasic": false,
        "amount": 1,
        "slotId": 9
    },
    {
        "id": 226,
        "slotName": "Headgear",
        "name": "Wizardly Hat",
        "isBasic": false,
        "amount": 1,
        "slotId": 9
    },
    {
        "id": 227,
        "slotName": "Headgear",
        "name": "Master Helm",
        "isBasic": false,
        "amount": 1,
        "slotId": 9
    },
    {
        "id": 228,
        "slotName": "Headgear",
        "name": "Ultimate Helm",
        "isBasic": false,
        "amount": 1,
        "slotId": 9
    },
    {
        "id": 229,
        "slotName": "Headgear",
        "name": "Nomad Bandana",
        "isBasic": false,
        "amount": 1,
        "slotId": 9
    },
    {
        "id": 230,
        "slotName": "Headgear",
        "name": "White Bandana",
        "isBasic": false,
        "amount": 1,
        "slotId": 9
    },
    {
        "id": 231,
        "slotName": "Left Hand",
        "name": "Bulletstorm L",
        "isBasic": false,
        "amount": 1,
        "slotId": 10
    },
    {
        "id": 232,
        "slotName": "Left Hand",
        "name": "Atomizer Bat L",
        "isBasic": false,
        "amount": 1,
        "slotId": 10
    },
    {
        "id": 233,
        "slotName": "Left Hand",
        "name": "Bullseye Sniper Rifle L",
        "isBasic": false,
        "amount": 1,
        "slotId": 10
    },
    {
        "id": 234,
        "slotName": "Left Hand",
        "name": "Common Axe L",
        "isBasic": false,
        "amount": 1,
        "slotId": 10
    },
    {
        "id": 235,
        "slotName": "Left Hand",
        "name": "Axe of Strings L",
        "isBasic": false,
        "amount": 1,
        "slotId": 10
    },
    {
        "id": 236,
        "slotName": "Left Hand",
        "name": "Tome of Incantations L",
        "isBasic": false,
        "amount": 1,
        "slotId": 10
    },
    {
        "id": 237,
        "slotName": "Left Hand",
        "name": "Common Broadsword L",
        "isBasic": false,
        "amount": 1,
        "slotId": 10
    },
    {
        "id": 238,
        "slotName": "Left Hand",
        "name": "Blue Flashfire Gun L",
        "isBasic": false,
        "amount": 1,
        "slotId": 10
    },
    {
        "id": 239,
        "slotName": "Left Hand",
        "name": "Massive Greatsword L",
        "isBasic": false,
        "amount": 1,
        "slotId": 10
    },
    {
        "id": 240,
        "slotName": "Left Hand",
        "name": "Stainless Chainsaw L",
        "isBasic": false,
        "amount": 1,
        "slotId": 10
    },
    {
        "id": 241,
        "slotName": "Left Hand",
        "name": "Savage Fangs L",
        "isBasic": false,
        "amount": 1,
        "slotId": 10
    },
    {
        "id": 242,
        "slotName": "Left Hand",
        "name": "Venomous Talons L",
        "isBasic": false,
        "amount": 1,
        "slotId": 10
    },
    {
        "id": 243,
        "slotName": "Left Hand",
        "name": "Night Hunter L",
        "isBasic": false,
        "amount": 1,
        "slotId": 10
    },
    {
        "id": 244,
        "slotName": "Left Hand",
        "name": "Crystal Sword L",
        "isBasic": false,
        "amount": 1,
        "slotId": 10
    },
    {
        "id": 245,
        "slotName": "Left Hand",
        "name": "Ichika's Doomblade L",
        "isBasic": false,
        "amount": 1,
        "slotId": 10
    },
    {
        "id": 246,
        "slotName": "Left Hand",
        "name": "Cyberpunk Katana L",
        "isBasic": false,
        "amount": 1,
        "slotId": 10
    },
    {
        "id": 247,
        "slotName": "Left Hand",
        "name": "Iron Fist L",
        "isBasic": false,
        "amount": 1,
        "slotId": 10
    },
    {
        "id": 248,
        "slotName": "Left Hand",
        "name": "Neuromantic Saber L",
        "isBasic": false,
        "amount": 1,
        "slotId": 10
    },
    {
        "id": 249,
        "slotName": "Left Hand",
        "name": "Vaporizer L",
        "isBasic": false,
        "amount": 1,
        "slotId": 10
    },
    {
        "id": 250,
        "slotName": "Left Hand",
        "name": "Cyberpunk Sword L",
        "isBasic": false,
        "amount": 1,
        "slotId": 10
    },
    {
        "id": 251,
        "slotName": "Left Hand",
        "name": "Cypher Sword L",
        "isBasic": false,
        "amount": 1,
        "slotId": 10
    },
    {
        "id": 252,
        "slotName": "Left Hand",
        "name": "Sand Falcon L",
        "isBasic": false,
        "amount": 1,
        "slotId": 10
    },
    {
        "id": 253,
        "slotName": "Left Hand",
        "name": "Common Sai L",
        "isBasic": false,
        "amount": 1,
        "slotId": 10
    },
    {
        "id": 254,
        "slotName": "Left Hand",
        "name": "Energy Blade L",
        "isBasic": false,
        "amount": 1,
        "slotId": 10
    },
    {
        "id": 255,
        "slotName": "Left Hand",
        "name": "Energy Sword L",
        "isBasic": false,
        "amount": 1,
        "slotId": 10
    },
    {
        "id": 256,
        "slotName": "Left Hand",
        "name": "Inferno L",
        "isBasic": false,
        "amount": 1,
        "slotId": 10
    },
    {
        "id": 257,
        "slotName": "Left Hand",
        "name": "Levitating Blade of Justice L",
        "isBasic": false,
        "amount": 1,
        "slotId": 10
    },
    {
        "id": 258,
        "slotName": "Left Hand",
        "name": "Flying Guillotine L",
        "isBasic": false,
        "amount": 1,
        "slotId": 10
    },
    {
        "id": 259,
        "slotName": "Left Hand",
        "name": "Dark Blade of Zulax L",
        "isBasic": false,
        "amount": 1,
        "slotId": 10
    },
    {
        "id": 260,
        "slotName": "Left Hand",
        "name": "Thunder Punch L",
        "isBasic": false,
        "amount": 1,
        "slotId": 10
    },
    {
        "id": 261,
        "slotName": "Left Hand",
        "name": "Shadow Striker L",
        "isBasic": false,
        "amount": 1,
        "slotId": 10
    },
    {
        "id": 262,
        "slotName": "Left Hand",
        "name": "Luminescent Gauntlets L",
        "isBasic": false,
        "amount": 1,
        "slotId": 10
    },
    {
        "id": 263,
        "slotName": "Left Hand",
        "name": "Radiant Manuscript L",
        "isBasic": false,
        "amount": 1,
        "slotId": 10
    },
    {
        "id": 264,
        "slotName": "Left Hand",
        "name": "Treasure Hunter's Delight L",
        "isBasic": false,
        "amount": 1,
        "slotId": 10
    },
    {
        "id": 265,
        "slotName": "Left Hand",
        "name": "The Caliber Saber L",
        "isBasic": false,
        "amount": 1,
        "slotId": 10
    },
    {
        "id": 266,
        "slotName": "Left Hand",
        "name": "The Light of the Heavens L",
        "isBasic": false,
        "amount": 1,
        "slotId": 10
    },
    {
        "id": 267,
        "slotName": "Left Hand",
        "name": "Heavy Machine Gun L",
        "isBasic": false,
        "amount": 1,
        "slotId": 10
    },
    {
        "id": 268,
        "slotName": "Left Hand",
        "name": "The Blade of Deep Thought L",
        "isBasic": false,
        "amount": 1,
        "slotId": 10
    },
    {
        "id": 269,
        "slotName": "Left Hand",
        "name": "Iron Fan L",
        "isBasic": false,
        "amount": 1,
        "slotId": 10
    },
    {
        "id": 270,
        "slotName": "Left Hand",
        "name": "Knight's Mark L",
        "isBasic": false,
        "amount": 1,
        "slotId": 10
    },
    {
        "id": 271,
        "slotName": "Left Hand",
        "name": "Flame Tongue L",
        "isBasic": false,
        "amount": 1,
        "slotId": 10
    },
    {
        "id": 272,
        "slotName": "Left Hand",
        "name": "Kite Shield L",
        "isBasic": false,
        "amount": 1,
        "slotId": 10
    },
    {
        "id": 273,
        "slotName": "Left Hand",
        "name": "Valorous Blade L",
        "isBasic": false,
        "amount": 1,
        "slotId": 10
    },
    {
        "id": 274,
        "slotName": "Left Hand",
        "name": "Noble Tail L",
        "isBasic": false,
        "amount": 1,
        "slotId": 10
    },
    {
        "id": 275,
        "slotName": "Left Hand",
        "name": "Shadow Spikes L",
        "isBasic": false,
        "amount": 1,
        "slotId": 10
    },
    {
        "id": 276,
        "slotName": "Left Hand",
        "name": "Vapor Darts L",
        "isBasic": false,
        "amount": 1,
        "slotId": 10
    },
    {
        "id": 277,
        "slotName": "Left Hand",
        "name": "Squire's Lance L",
        "isBasic": false,
        "amount": 1,
        "slotId": 10
    },
    {
        "id": 278,
        "slotName": "Left Hand",
        "name": "Hacker Chase Cyberdeck 88 L",
        "isBasic": false,
        "amount": 1,
        "slotId": 10
    },
    {
        "id": 279,
        "slotName": "Left Hand",
        "name": "Lich Sword L",
        "isBasic": false,
        "amount": 1,
        "slotId": 10
    },
    {
        "id": 280,
        "slotName": "Left Hand",
        "name": "Dragon's Fury L",
        "isBasic": false,
        "amount": 1,
        "slotId": 10
    },
    {
        "id": 281,
        "slotName": "Left Hand",
        "name": "Widowmaker L",
        "isBasic": false,
        "amount": 1,
        "slotId": 10
    },
    {
        "id": 282,
        "slotName": "Left Hand",
        "name": "Cudgel of Paul the Wise L",
        "isBasic": false,
        "amount": 1,
        "slotId": 10
    },
    {
        "id": 283,
        "slotName": "Left Hand",
        "name": "Grimoire of Arcana L",
        "isBasic": false,
        "amount": 1,
        "slotId": 10
    },
    {
        "id": 284,
        "slotName": "Left Hand",
        "name": "Staff of the Archmage L",
        "isBasic": false,
        "amount": 1,
        "slotId": 10
    },
    {
        "id": 285,
        "slotName": "Left Hand",
        "name": "Netherworld Wand L",
        "isBasic": true,
        "amount": 1,
        "slotId": 10
    },
    {
        "id": 286,
        "slotName": "Left Hand",
        "name": "Constellation Scribe L",
        "isBasic": true,
        "amount": 1,
        "slotId": 10
    },
    {
        "id": 287,
        "slotName": "Left Hand",
        "name": "Shaken Not Stirred L",
        "isBasic": false,
        "amount": 1,
        "slotId": 10
    },
    {
        "id": 288,
        "slotName": "Left Hand",
        "name": "Gadgeteer's Multitool L",
        "isBasic": false,
        "amount": 1,
        "slotId": 10
    },
    {
        "id": 289,
        "slotName": "Left Hand",
        "name": "Gravimetric Cannon L",
        "isBasic": false,
        "amount": 1,
        "slotId": 10
    },
    {
        "id": 290,
        "slotName": "Left Hand",
        "name": "VenkaTech Mk2000 L",
        "isBasic": false,
        "amount": 1,
        "slotId": 10
    },
    {
        "id": 291,
        "slotName": "Left Hand",
        "name": "VenkaTech Mk2000 L",
        "isBasic": false,
        "amount": 1,
        "slotId": 10
    },
    {
        "id": 292,
        "slotName": "Left Hand",
        "name": "Peacemaker L",
        "isBasic": false,
        "amount": 1,
        "slotId": 10
    },
    {
        "id": 293,
        "slotName": "Left Hand",
        "name": "Arcane Revolver L",
        "isBasic": false,
        "amount": 1,
        "slotId": 10
    },
    {
        "id": 294,
        "slotName": "Left Hand",
        "name": "Scorpion Blade L",
        "isBasic": false,
        "amount": 1,
        "slotId": 10
    },
    {
        "id": 295,
        "slotName": "Left Hand",
        "name": "Endless Potion of Possibilities L",
        "isBasic": false,
        "amount": 1,
        "slotId": 10
    },
    {
        "id": 296,
        "slotName": "Left Hand",
        "name": "Sacred Vessel of the Divine L",
        "isBasic": false,
        "amount": 1,
        "slotId": 10
    },
    {
        "id": 297,
        "slotName": "Left Hand",
        "name": "Gavel of Sacred Judgment L",
        "isBasic": false,
        "amount": 1,
        "slotId": 10
    },
    {
        "id": 298,
        "slotName": "Left Hand",
        "name": "Magnetronic Bazooka L",
        "isBasic": false,
        "amount": 1,
        "slotId": 10
    },
    {
        "id": 299,
        "slotName": "Left Hand",
        "name": "Thunderbolt L",
        "isBasic": false,
        "amount": 1,
        "slotId": 10
    },
    {
        "id": 300,
        "slotName": "Left Hand",
        "name": "Ian's Disintegrator L",
        "isBasic": false,
        "amount": 1,
        "slotId": 10
    },
    {
        "id": 301,
        "slotName": "Left Hand",
        "name": "Doom Bringer L",
        "isBasic": false,
        "amount": 1,
        "slotId": 10
    },
    {
        "id": 302,
        "slotName": "Left Hand",
        "name": "Blade of Honor L",
        "isBasic": false,
        "amount": 1,
        "slotId": 10
    },
    {
        "id": 303,
        "slotName": "Left Hand",
        "name": "Royal Wand of Power L",
        "isBasic": true,
        "amount": 1,
        "slotId": 10
    },
    {
        "id": 304,
        "slotName": "Left Hand",
        "name": "Vile Scepter of Janeman the Mad L",
        "isBasic": true,
        "amount": 1,
        "slotId": 10
    },
    {
        "id": 305,
        "slotName": "Left Hand",
        "name": "Screw Turner L",
        "isBasic": false,
        "amount": 1,
        "slotId": 10
    },
    {
        "id": 306,
        "slotName": "Left Hand",
        "name": "Death Scythe L",
        "isBasic": false,
        "amount": 1,
        "slotId": 10
    },
    {
        "id": 307,
        "slotName": "Left Hand",
        "name": "Reaperblade L",
        "isBasic": false,
        "amount": 1,
        "slotId": 10
    },
    {
        "id": 308,
        "slotName": "Left Hand",
        "name": "Shining Barrier L",
        "isBasic": false,
        "amount": 1,
        "slotId": 10
    },
    {
        "id": 309,
        "slotName": "Left Hand",
        "name": "Shards of Shadow L",
        "isBasic": false,
        "amount": 1,
        "slotId": 10
    },
    {
        "id": 310,
        "slotName": "Left Hand",
        "name": "Serpent Scepter L",
        "isBasic": false,
        "amount": 1,
        "slotId": 10
    },
    {
        "id": 311,
        "slotName": "Left Hand",
        "name": "Fizzy Fury L",
        "isBasic": false,
        "amount": 1,
        "slotId": 10
    },
    {
        "id": 312,
        "slotName": "Left Hand",
        "name": "Annihilator L",
        "isBasic": false,
        "amount": 1,
        "slotId": 10
    },
    {
        "id": 313,
        "slotName": "Left Hand",
        "name": "Resonating Blade L",
        "isBasic": false,
        "amount": 1,
        "slotId": 10
    },
    {
        "id": 314,
        "slotName": "Left Hand",
        "name": "Magna-Staff L",
        "isBasic": false,
        "amount": 1,
        "slotId": 10
    },
    {
        "id": 315,
        "slotName": "Left Hand",
        "name": "Ranger's Edge L",
        "isBasic": false,
        "amount": 1,
        "slotId": 10
    },
    {
        "id": 316,
        "slotName": "Left Hand",
        "name": "Edge of the Eastern Winds L",
        "isBasic": false,
        "amount": 1,
        "slotId": 10
    },
    {
        "id": 317,
        "slotName": "Left Hand",
        "name": "Artifact Hunter L",
        "isBasic": false,
        "amount": 1,
        "slotId": 10
    },
    {
        "id": 318,
        "slotName": "Left Hand",
        "name": "Travis Sword L",
        "isBasic": false,
        "amount": 1,
        "slotId": 10
    },
    {
        "id": 319,
        "slotName": "Left Hand",
        "name": "Neptune's Wrath L",
        "isBasic": false,
        "amount": 1,
        "slotId": 10
    },
    {
        "id": 320,
        "slotName": "Left Hand",
        "name": "Poseidon's Demise L",
        "isBasic": false,
        "amount": 1,
        "slotId": 10
    },
    {
        "id": 321,
        "slotName": "Left Hand",
        "name": "Sturdy Branch L",
        "isBasic": false,
        "amount": 1,
        "slotId": 10
    },
    {
        "id": 322,
        "slotName": "Left Hand",
        "name": "Handy Stick L",
        "isBasic": false,
        "amount": 1,
        "slotId": 10
    },
    {
        "id": 323,
        "slotName": "Left Hand",
        "name": "Discarded Rod L",
        "isBasic": false,
        "amount": 1,
        "slotId": 10
    },
    {
        "id": 324,
        "slotName": "Left Hand",
        "name": "Blade of Duty L",
        "isBasic": false,
        "amount": 1,
        "slotId": 10
    },
    {
        "id": 325,
        "slotName": "Left Hand",
        "name": "Maul of Blood L",
        "isBasic": false,
        "amount": 1,
        "slotId": 10
    },
    {
        "id": 326,
        "slotName": "Left Hand",
        "name": "Engineer's Autowrench L",
        "isBasic": false,
        "amount": 1,
        "slotId": 10
    },
    {
        "id": 327,
        "slotName": "Left Hand",
        "name": "Mechanic's Handy Wrench L",
        "isBasic": false,
        "amount": 1,
        "slotId": 10
    },
    {
        "id": 328,
        "slotName": "Mouth",
        "name": "Beard",
        "isBasic": false,
        "amount": 1,
        "slotId": 3
    },
    {
        "id": 329,
        "slotName": "Mouth",
        "name": "Smile",
        "isBasic": false,
        "amount": 1,
        "slotId": 3
    },
    {
        "id": 330,
        "slotName": "Mouth",
        "name": "Flat",
        "isBasic": false,
        "amount": 1,
        "slotId": 3
    },
    {
        "id": 331,
        "slotName": "Mouth",
        "name": "Frown",
        "isBasic": false,
        "amount": 1,
        "slotId": 3
    },
    {
        "id": 332,
        "slotName": "Mouth",
        "name": "Full Beard",
        "isBasic": false,
        "amount": 1,
        "slotId": 3
    },
    {
        "id": 333,
        "slotName": "Mouth",
        "name": "Slight Smile",
        "isBasic": false,
        "amount": 1,
        "slotId": 3
    },
    {
        "id": 334,
        "slotName": "Mouth",
        "name": "Moustache",
        "isBasic": false,
        "amount": 1,
        "slotId": 3
    },
    {
        "id": 335,
        "slotName": "Mouth",
        "name": "Okay",
        "isBasic": false,
        "amount": 1,
        "slotId": 3
    },
    {
        "id": 336,
        "slotName": "Mouth",
        "name": "Fang",
        "isBasic": false,
        "amount": 1,
        "slotId": 3
    },
    {
        "id": 337,
        "slotName": "Mouth",
        "name": "Pucker",
        "isBasic": false,
        "amount": 1,
        "slotId": 3
    },
    {
        "id": 338,
        "slotName": "Mouth",
        "name": "Sad",
        "isBasic": false,
        "amount": 1,
        "slotId": 3
    },
    {
        "id": 339,
        "slotName": "Mouth",
        "name": "Shout",
        "isBasic": false,
        "amount": 1,
        "slotId": 3
    },
    {
        "id": 340,
        "slotName": "Mouth",
        "name": "Smile",
        "isBasic": false,
        "amount": 1,
        "slotId": 3
    },
    {
        "id": 341,
        "slotName": "Mouth",
        "name": "Big Smile",
        "isBasic": false,
        "amount": 1,
        "slotId": 3
    },
    {
        "id": 342,
        "slotName": "Mouth",
        "name": "Toothless",
        "isBasic": false,
        "amount": 1,
        "slotId": 3
    },
    {
        "id": 343,
        "slotName": "Mouth",
        "name": "uWu",
        "isBasic": false,
        "amount": 1,
        "slotId": 3
    },
    {
        "id": 344,
        "slotName": "Mouth",
        "name": "Vampire",
        "isBasic": false,
        "amount": 1,
        "slotId": 3
    },
    {
        "id": 345,
        "slotName": "Mouth",
        "name": "Very Sad",
        "isBasic": false,
        "amount": 1,
        "slotId": 3
    },
    {
        "id": 346,
        "slotName": "Right Hand",
        "name": "Bulletstorm R",
        "isBasic": false,
        "amount": 1,
        "slotId": 11
    },
    {
        "id": 347,
        "slotName": "Right Hand",
        "name": "Atomizer Bat R",
        "isBasic": false,
        "amount": 1,
        "slotId": 11
    },
    {
        "id": 348,
        "slotName": "Right Hand",
        "name": "Bullseye Sniper Rifle R",
        "isBasic": false,
        "amount": 1,
        "slotId": 11
    },
    {
        "id": 349,
        "slotName": "Right Hand",
        "name": "Common Axe R",
        "isBasic": false,
        "amount": 1,
        "slotId": 11
    },
    {
        "id": 350,
        "slotName": "Right Hand",
        "name": "Axe of Strings R",
        "isBasic": false,
        "amount": 1,
        "slotId": 11
    },
    {
        "id": 351,
        "slotName": "Right Hand",
        "name": "Tome of Incantations R",
        "isBasic": false,
        "amount": 1,
        "slotId": 11
    },
    {
        "id": 352,
        "slotName": "Right Hand",
        "name": "Common Broadsword R",
        "isBasic": false,
        "amount": 1,
        "slotId": 11
    },
    {
        "id": 353,
        "slotName": "Right Hand",
        "name": "Blue Flashfire Gun R",
        "isBasic": false,
        "amount": 1,
        "slotId": 11
    },
    {
        "id": 354,
        "slotName": "Right Hand",
        "name": "Massive Greatsword R",
        "isBasic": false,
        "amount": 1,
        "slotId": 11
    },
    {
        "id": 355,
        "slotName": "Right Hand",
        "name": "Stainless Chainsaw R",
        "isBasic": false,
        "amount": 1,
        "slotId": 11
    },
    {
        "id": 356,
        "slotName": "Right Hand",
        "name": "Savage Fangs R",
        "isBasic": false,
        "amount": 1,
        "slotId": 11
    },
    {
        "id": 357,
        "slotName": "Right Hand",
        "name": "Venomous Talons R",
        "isBasic": false,
        "amount": 1,
        "slotId": 11
    },
    {
        "id": 358,
        "slotName": "Right Hand",
        "name": "Night Hunter R",
        "isBasic": false,
        "amount": 1,
        "slotId": 11
    },
    {
        "id": 359,
        "slotName": "Right Hand",
        "name": "Crystal Sword R",
        "isBasic": false,
        "amount": 1,
        "slotId": 11
    },
    {
        "id": 360,
        "slotName": "Right Hand",
        "name": "Ichika's Doomblade R",
        "isBasic": false,
        "amount": 1,
        "slotId": 11
    },
    {
        "id": 361,
        "slotName": "Right Hand",
        "name": "Cyberpunk Katana R",
        "isBasic": false,
        "amount": 1,
        "slotId": 11
    },
    {
        "id": 362,
        "slotName": "Right Hand",
        "name": "Iron Fist R",
        "isBasic": false,
        "amount": 1,
        "slotId": 11
    },
    {
        "id": 363,
        "slotName": "Right Hand",
        "name": "Neuromantic Saber R",
        "isBasic": false,
        "amount": 1,
        "slotId": 11
    },
    {
        "id": 364,
        "slotName": "Right Hand",
        "name": "Vaporizer R",
        "isBasic": false,
        "amount": 1,
        "slotId": 11
    },
    {
        "id": 365,
        "slotName": "Right Hand",
        "name": "Cyberpunk Sword R",
        "isBasic": false,
        "amount": 1,
        "slotId": 11
    },
    {
        "id": 366,
        "slotName": "Right Hand",
        "name": "Cypher Sword R",
        "isBasic": false,
        "amount": 1,
        "slotId": 11
    },
    {
        "id": 367,
        "slotName": "Right Hand",
        "name": "Sand Falcon R",
        "isBasic": false,
        "amount": 1,
        "slotId": 11
    },
    {
        "id": 368,
        "slotName": "Right Hand",
        "name": "Common Sai R",
        "isBasic": false,
        "amount": 1,
        "slotId": 11
    },
    {
        "id": 369,
        "slotName": "Right Hand",
        "name": "Energy Blade R",
        "isBasic": false,
        "amount": 1,
        "slotId": 11
    },
    {
        "id": 370,
        "slotName": "Right Hand",
        "name": "Energy Sword R",
        "isBasic": false,
        "amount": 1,
        "slotId": 11
    },
    {
        "id": 371,
        "slotName": "Right Hand",
        "name": "Inferno R",
        "isBasic": false,
        "amount": 1,
        "slotId": 11
    },
    {
        "id": 372,
        "slotName": "Right Hand",
        "name": "Levitating Blade of Justice R",
        "isBasic": false,
        "amount": 1,
        "slotId": 11
    },
    {
        "id": 373,
        "slotName": "Right Hand",
        "name": "Flying Guillotine R",
        "isBasic": false,
        "amount": 1,
        "slotId": 11
    },
    {
        "id": 374,
        "slotName": "Right Hand",
        "name": "Dark Blade of Zulax R",
        "isBasic": false,
        "amount": 1,
        "slotId": 11
    },
    {
        "id": 375,
        "slotName": "Right Hand",
        "name": "Shadow Striker R",
        "isBasic": false,
        "amount": 1,
        "slotId": 11
    },
    {
        "id": 376,
        "slotName": "Right Hand",
        "name": "Luminescent Gauntlets R",
        "isBasic": false,
        "amount": 1,
        "slotId": 11
    },
    {
        "id": 377,
        "slotName": "Right Hand",
        "name": "Radiant Manuscript R",
        "isBasic": false,
        "amount": 1,
        "slotId": 11
    },
    {
        "id": 378,
        "slotName": "Right Hand",
        "name": "Treasure Hunter's Delight R",
        "isBasic": false,
        "amount": 1,
        "slotId": 11
    },
    {
        "id": 379,
        "slotName": "Right Hand",
        "name": "Explosive Rain R",
        "isBasic": false,
        "amount": 1,
        "slotId": 11
    },
    {
        "id": 380,
        "slotName": "Right Hand",
        "name": "The Caliber Saber R",
        "isBasic": false,
        "amount": 1,
        "slotId": 11
    },
    {
        "id": 381,
        "slotName": "Right Hand",
        "name": "The Light of the Heavens R",
        "isBasic": true,
        "amount": 1,
        "slotId": 11
    },
    {
        "id": 382,
        "slotName": "Right Hand",
        "name": "Heavy Machine Gun R",
        "isBasic": true,
        "amount": 1,
        "slotId": 11
    },
    {
        "id": 383,
        "slotName": "Right Hand",
        "name": "The Blade of Deep Thought R",
        "isBasic": true,
        "amount": 1,
        "slotId": 11
    },
    {
        "id": 384,
        "slotName": "Right Hand",
        "name": "Iron Fan R",
        "isBasic": false,
        "amount": 1,
        "slotId": 11
    },
    {
        "id": 385,
        "slotName": "Right Hand",
        "name": "Knight's Mark R",
        "isBasic": false,
        "amount": 1,
        "slotId": 11
    },
    {
        "id": 386,
        "slotName": "Right Hand",
        "name": "Flame Tongue R",
        "isBasic": false,
        "amount": 1,
        "slotId": 11
    },
    {
        "id": 387,
        "slotName": "Right Hand",
        "name": "Kite Shield R",
        "isBasic": false,
        "amount": 1,
        "slotId": 11
    },
    {
        "id": 388,
        "slotName": "Right Hand",
        "name": "Valorous Blade R",
        "isBasic": false,
        "amount": 1,
        "slotId": 11
    },
    {
        "id": 389,
        "slotName": "Right Hand",
        "name": "Noble Tail R",
        "isBasic": true,
        "amount": 1,
        "slotId": 11
    },
    {
        "id": 390,
        "slotName": "Right Hand",
        "name": "Shadow Spikes R",
        "isBasic": true,
        "amount": 1,
        "slotId": 11
    },
    {
        "id": 391,
        "slotName": "Right Hand",
        "name": "Vapor Darts R",
        "isBasic": false,
        "amount": 1,
        "slotId": 11
    },
    {
        "id": 392,
        "slotName": "Right Hand",
        "name": "Squire's Lance R",
        "isBasic": false,
        "amount": 1,
        "slotId": 11
    },
    {
        "id": 393,
        "slotName": "Right Hand",
        "name": "Hacker Chase Cyberdeck 88 R",
        "isBasic": false,
        "amount": 1,
        "slotId": 11
    },
    {
        "id": 394,
        "slotName": "Right Hand",
        "name": "Lich Sword R",
        "isBasic": false,
        "amount": 1,
        "slotId": 11
    },
    {
        "id": 395,
        "slotName": "Right Hand",
        "name": "Widowmaker R",
        "isBasic": false,
        "amount": 1,
        "slotId": 11
    },
    {
        "id": 396,
        "slotName": "Right Hand",
        "name": "Dragon's Fury R",
        "isBasic": false,
        "amount": 1,
        "slotId": 11
    },
    {
        "id": 397,
        "slotName": "Right Hand",
        "name": "Cudgel of Paul the Wise R",
        "isBasic": false,
        "amount": 1,
        "slotId": 11
    },
    {
        "id": 398,
        "slotName": "Right Hand",
        "name": "Grimoire of Arcana R",
        "isBasic": false,
        "amount": 1,
        "slotId": 11
    },
    {
        "id": 399,
        "slotName": "Right Hand",
        "name": "Staff of the Archmage R",
        "isBasic": false,
        "amount": 1,
        "slotId": 11
    },
    {
        "id": 400,
        "slotName": "Right Hand",
        "name": "Netherworld Wand R",
        "isBasic": false,
        "amount": 1,
        "slotId": 11
    },
    {
        "id": 401,
        "slotName": "Right Hand",
        "name": "Constellation Scribe R",
        "isBasic": false,
        "amount": 1,
        "slotId": 11
    },
    {
        "id": 402,
        "slotName": "Right Hand",
        "name": "Shaken Not Stirred R",
        "isBasic": false,
        "amount": 1,
        "slotId": 11
    },
    {
        "id": 403,
        "slotName": "Right Hand",
        "name": "Gadgeteer's Multitool R",
        "isBasic": false,
        "amount": 1,
        "slotId": 11
    },
    {
        "id": 404,
        "slotName": "Right Hand",
        "name": "Gravimetric Cannon R",
        "isBasic": false,
        "amount": 1,
        "slotId": 11
    },
    {
        "id": 405,
        "slotName": "Right Hand",
        "name": "Thunder Punch R",
        "isBasic": false,
        "amount": 1,
        "slotId": 11
    },
    {
        "id": 406,
        "slotName": "Right Hand",
        "name": "VenkaTech Mk2000 R",
        "isBasic": false,
        "amount": 1,
        "slotId": 11
    },
    {
        "id": 407,
        "slotName": "Right Hand",
        "name": "VenkaTech Mk2000 R",
        "isBasic": false,
        "amount": 1,
        "slotId": 11
    },
    {
        "id": 408,
        "slotName": "Right Hand",
        "name": "Peacemaker R",
        "isBasic": false,
        "amount": 1,
        "slotId": 11
    },
    {
        "id": 409,
        "slotName": "Right Hand",
        "name": "Arcane Revolver R",
        "isBasic": false,
        "amount": 1,
        "slotId": 11
    },
    {
        "id": 410,
        "slotName": "Right Hand",
        "name": "Scorpion Blade R",
        "isBasic": false,
        "amount": 1,
        "slotId": 11
    },
    {
        "id": 411,
        "slotName": "Right Hand",
        "name": "Endless Potion of Possibilities R",
        "isBasic": false,
        "amount": 1,
        "slotId": 11
    },
    {
        "id": 412,
        "slotName": "Right Hand",
        "name": "Sacred Vessel of the Divine R",
        "isBasic": false,
        "amount": 1,
        "slotId": 11
    },
    {
        "id": 413,
        "slotName": "Right Hand",
        "name": "Gavel of Sacred Judgment R",
        "isBasic": false,
        "amount": 1,
        "slotId": 11
    },
    {
        "id": 414,
        "slotName": "Right Hand",
        "name": "Magnetronic Bazooka R",
        "isBasic": false,
        "amount": 1,
        "slotId": 11
    },
    {
        "id": 415,
        "slotName": "Right Hand",
        "name": "Thunderbolt R",
        "isBasic": false,
        "amount": 1,
        "slotId": 11
    },
    {
        "id": 416,
        "slotName": "Right Hand",
        "name": "Ian's Disintegrator R",
        "isBasic": false,
        "amount": 1,
        "slotId": 11
    },
    {
        "id": 417,
        "slotName": "Right Hand",
        "name": "Doom Bringer R",
        "isBasic": false,
        "amount": 1,
        "slotId": 11
    },
    {
        "id": 418,
        "slotName": "Right Hand",
        "name": "Blade of Honor R",
        "isBasic": false,
        "amount": 1,
        "slotId": 11
    },
    {
        "id": 419,
        "slotName": "Right Hand",
        "name": "Royal Wand of Power R",
        "isBasic": false,
        "amount": 1,
        "slotId": 11
    },
    {
        "id": 420,
        "slotName": "Right Hand",
        "name": "Vile Scepter of Janeman the Mad R",
        "isBasic": false,
        "amount": 1,
        "slotId": 11
    },
    {
        "id": 421,
        "slotName": "Right Hand",
        "name": "Screw Turner R",
        "isBasic": false,
        "amount": 1,
        "slotId": 11
    },
    {
        "id": 422,
        "slotName": "Right Hand",
        "name": "Death Scythe R",
        "isBasic": false,
        "amount": 1,
        "slotId": 11
    },
    {
        "id": 423,
        "slotName": "Right Hand",
        "name": "Reaperblade R",
        "isBasic": false,
        "amount": 1,
        "slotId": 11
    },
    {
        "id": 424,
        "slotName": "Right Hand",
        "name": "Shining Barrier R",
        "isBasic": false,
        "amount": 1,
        "slotId": 11
    },
    {
        "id": 425,
        "slotName": "Right Hand",
        "name": "Shards of Shadow R",
        "isBasic": false,
        "amount": 1,
        "slotId": 11
    },
    {
        "id": 426,
        "slotName": "Right Hand",
        "name": "Serpent Scepter R",
        "isBasic": false,
        "amount": 1,
        "slotId": 11
    },
    {
        "id": 427,
        "slotName": "Right Hand",
        "name": "Fizzy Fury R",
        "isBasic": false,
        "amount": 1,
        "slotId": 11
    },
    {
        "id": 428,
        "slotName": "Right Hand",
        "name": "Annihilator R",
        "isBasic": false,
        "amount": 1,
        "slotId": 11
    },
    {
        "id": 429,
        "slotName": "Right Hand",
        "name": "Resonating Blade R",
        "isBasic": false,
        "amount": 1,
        "slotId": 11
    },
    {
        "id": 430,
        "slotName": "Right Hand",
        "name": "Magna-Staff R",
        "isBasic": false,
        "amount": 1,
        "slotId": 11
    },
    {
        "id": 431,
        "slotName": "Right Hand",
        "name": "Ranger's Edge R",
        "isBasic": false,
        "amount": 1,
        "slotId": 11
    },
    {
        "id": 432,
        "slotName": "Right Hand",
        "name": "Edge of the Eastern Winds R",
        "isBasic": false,
        "amount": 1,
        "slotId": 11
    },
    {
        "id": 433,
        "slotName": "Right Hand",
        "name": "Artifact Hunter R",
        "isBasic": false,
        "amount": 1,
        "slotId": 11
    },
    {
        "id": 434,
        "slotName": "Right Hand",
        "name": "Travis Sword R",
        "isBasic": false,
        "amount": 1,
        "slotId": 11
    },
    {
        "id": 435,
        "slotName": "Right Hand",
        "name": "Neptune's Wrath R",
        "isBasic": false,
        "amount": 1,
        "slotId": 11
    },
    {
        "id": 436,
        "slotName": "Right Hand",
        "name": "Poseidon's Demise R",
        "isBasic": false,
        "amount": 1,
        "slotId": 11
    },
    {
        "id": 437,
        "slotName": "Right Hand",
        "name": "Sturdy Branch R",
        "isBasic": false,
        "amount": 1,
        "slotId": 11
    },
    {
        "id": 438,
        "slotName": "Right Hand",
        "name": "Handy Stick R",
        "isBasic": false,
        "amount": 1,
        "slotId": 11
    },
    {
        "id": 439,
        "slotName": "Right Hand",
        "name": "Discarded Rod R",
        "isBasic": false,
        "amount": 1,
        "slotId": 11
    },
    {
        "id": 440,
        "slotName": "Right Hand",
        "name": "Blade of Duty R",
        "isBasic": false,
        "amount": 1,
        "slotId": 11
    },
    {
        "id": 441,
        "slotName": "Right Hand",
        "name": "Maul of Blood R",
        "isBasic": false,
        "amount": 1,
        "slotId": 11
    },
    {
        "id": 442,
        "slotName": "Right Hand",
        "name": "Engineer's Autowrench R",
        "isBasic": false,
        "amount": 1,
        "slotId": 11
    },
    {
        "id": 443,
        "slotName": "Right Hand",
        "name": "Mechanic's Handy Wrench R",
        "isBasic": false,
        "amount": 1,
        "slotId": 11
    },
    {
        "id": 444,
        "slotName": "Shadow",
        "name": "",
        "isBasic": false,
        "amount": 1,
        "slotId": 4
    },
    {
        "id": 445,
        "slotName": "Skin",
        "name": "",
        "isBasic": false,
        "amount": 1,
        "slotId": 5
    },
    {
        "id": 446,
        "slotName": "Skin",
        "name": "",
        "isBasic": false,
        "amount": 1,
        "slotId": 5
    },
    {
        "id": 447,
        "slotName": "Skin",
        "name": "",
        "isBasic": false,
        "amount": 1,
        "slotId": 5
    },
    {
        "id": 448,
        "slotName": "Skin",
        "name": "",
        "isBasic": false,
        "amount": 1,
        "slotId": 5
    },
    {
        "id": 449,
        "slotName": "Skin",
        "name": "",
        "isBasic": false,
        "amount": 1,
        "slotId": 5
    },
    {
        "id": 450,
        "slotName": "Skin",
        "name": "",
        "isBasic": false,
        "amount": 1,
        "slotId": 5
    },
    {
        "id": 451,
        "slotName": "Skin",
        "name": "",
        "isBasic": true,
        "amount": 1,
        "slotId": 5
    },
    {
        "id": 452,
        "slotName": "Skin",
        "name": "",
        "isBasic": true,
        "amount": 1,
        "slotId": 5
    },
    {
        "id": 453,
        "slotName": "Skin",
        "name": "",
        "isBasic": true,
        "amount": 1,
        "slotId": 5
    },
    {
        "id": 454,
        "slotName": "Skin",
        "name": "",
        "isBasic": true,
        "amount": 1,
        "slotId": 5
    },
    {
        "id": 455,
        "slotName": "Skin",
        "name": "",
        "isBasic": true,
        "amount": 1,
        "slotId": 5
    },
    {
        "id": 456,
        "slotName": "Skin",
        "name": "",
        "isBasic": true,
        "amount": 1,
        "slotId": 5
    },
    {
        "id": 457,
        "slotName": "Skin",
        "name": "",
        "isBasic": true,
        "amount": 1,
        "slotId": 5
    },
    {
        "id": 458,
        "slotName": "Skin",
        "name": "",
        "isBasic": true,
        "amount": 1,
        "slotId": 5
    },
    {
        "id": 459,
        "slotName": "Skin",
        "name": "",
        "isBasic": true,
        "amount": 1,
        "slotId": 5
    },
    {
        "id": 460,
        "slotName": "Skin",
        "name": "",
        "isBasic": true,
        "amount": 1,
        "slotId": 5
    },
    {
        "id": 461,
        "slotName": "Skin",
        "name": "",
        "isBasic": true,
        "amount": 1,
        "slotId": 5
    },
    {
        "id": 462,
        "slotName": "Skin",
        "name": "",
        "isBasic": true,
        "amount": 1,
        "slotId": 5
    },
    {
        "id": 463,
        "slotName": "Skin",
        "name": "",
        "isBasic": true,
        "amount": 1,
        "slotId": 5
    },
    {
        "id": 464,
        "slotName": "Top",
        "name": "Academy Robe",
        "isBasic": true,
        "amount": 1,
        "slotId": 13
    },
    {
        "id": 465,
        "slotName": "Top",
        "name": "Dark Arts Robe",
        "isBasic": true,
        "amount": 1,
        "slotId": 13
    },
    {
        "id": 466,
        "slotName": "Top",
        "name": "Diana Armor",
        "isBasic": false,
        "amount": 1,
        "slotId": 13
    },
    {
        "id": 467,
        "slotName": "Top",
        "name": "Honor Wrappings",
        "isBasic": false,
        "amount": 1,
        "slotId": 13
    },
    {
        "id": 468,
        "slotName": "Top",
        "name": "Coman Armor",
        "isBasic": false,
        "amount": 1,
        "slotId": 13
    },
    {
        "id": 469,
        "slotName": "Top",
        "name": "Hacker Hoodie",
        "isBasic": false,
        "amount": 1,
        "slotId": 13
    },
    {
        "id": 470,
        "slotName": "Top",
        "name": "Matrix Jacket",
        "isBasic": false,
        "amount": 1,
        "slotId": 13
    },
    {
        "id": 471,
        "slotName": "Top",
        "name": "Muscle Shirt",
        "isBasic": false,
        "amount": 1,
        "slotId": 13
    },
    {
        "id": 472,
        "slotName": "Top",
        "name": "Bloody Armor",
        "isBasic": false,
        "amount": 1,
        "slotId": 13
    },
    {
        "id": 473,
        "slotName": "Top",
        "name": "Galactic Armor",
        "isBasic": false,
        "amount": 1,
        "slotId": 13
    },
    {
        "id": 474,
        "slotName": "Top",
        "name": "Corporal Shirt",
        "isBasic": false,
        "amount": 1,
        "slotId": 13
    },
    {
        "id": 475,
        "slotName": "Top",
        "name": "Sky Shirt",
        "isBasic": false,
        "amount": 1,
        "slotId": 13
    },
    {
        "id": 476,
        "slotName": "Top",
        "name": "Pooshirt",
        "isBasic": false,
        "amount": 1,
        "slotId": 13
    },
    {
        "id": 477,
        "slotName": "Top",
        "name": "Galahad Armor",
        "isBasic": false,
        "amount": 1,
        "slotId": 13
    },
    {
        "id": 478,
        "slotName": "Top",
        "name": "Basic Robes",
        "isBasic": false,
        "amount": 1,
        "slotId": 13
    },
    {
        "id": 479,
        "slotName": "Top",
        "name": "Rescued Armor",
        "isBasic": false,
        "amount": 1,
        "slotId": 13
    },
    {
        "id": 480,
        "slotName": "Top",
        "name": "Shadow Runner Armor",
        "isBasic": false,
        "amount": 1,
        "slotId": 13
    },
    {
        "id": 481,
        "slotName": "Top",
        "name": "Labyrinth Armor",
        "isBasic": false,
        "amount": 1,
        "slotId": 13
    },
    {
        "id": 482,
        "slotName": "Top",
        "name": "Tiamat Armor",
        "isBasic": false,
        "amount": 1,
        "slotId": 13
    },
    {
        "id": 483,
        "slotName": "Top",
        "name": "Adams Armor",
        "isBasic": false,
        "amount": 1,
        "slotId": 13
    },
    {
        "id": 484,
        "slotName": "Top",
        "name": "Bond Armor",
        "isBasic": false,
        "amount": 1,
        "slotId": 13
    },
    {
        "id": 485,
        "slotName": "Top",
        "name": "Midas Armor",
        "isBasic": false,
        "amount": 1,
        "slotId": 13
    },
    {
        "id": 486,
        "slotName": "Top",
        "name": "Arsenal Armor",
        "isBasic": false,
        "amount": 1,
        "slotId": 13
    },
    {
        "id": 487,
        "slotName": "Top",
        "name": "Guileless Shirt",
        "isBasic": false,
        "amount": 1,
        "slotId": 13
    },
    {
        "id": 488,
        "slotName": "Top",
        "name": "Romanova Armor",
        "isBasic": false,
        "amount": 1,
        "slotId": 13
    },
    {
        "id": 489,
        "slotName": "Top",
        "name": "Bleached Robe",
        "isBasic": false,
        "amount": 1,
        "slotId": 13
    },
    {
        "id": 490,
        "slotName": "Top",
        "name": "Ayane Robe",
        "isBasic": false,
        "amount": 1,
        "slotId": 13
    },
    {
        "id": 491,
        "slotName": "Top",
        "name": "Arthur Breastplate",
        "isBasic": false,
        "amount": 1,
        "slotId": 13
    },
    {
        "id": 492,
        "slotName": "Top",
        "name": "Kunoichi Armor",
        "isBasic": false,
        "amount": 1,
        "slotId": 13
    },
    {
        "id": 493,
        "slotName": "Top",
        "name": "Archlich Robe",
        "isBasic": false,
        "amount": 1,
        "slotId": 13
    },
    {
        "id": 494,
        "slotName": "Top",
        "name": "Merlin Robes",
        "isBasic": false,
        "amount": 1,
        "slotId": 13
    },
    {
        "id": 495,
        "slotName": "Top",
        "name": "Spartan Armor",
        "isBasic": false,
        "amount": 1,
        "slotId": 13
    },
    {
        "id": 496,
        "slotName": "Top",
        "name": "Techxpert Armor",
        "isBasic": false,
        "amount": 1,
        "slotId": 13
    },
    {
        "id": 497,
        "slotName": "Top",
        "name": "Training Tank (Blue)",
        "isBasic": false,
        "amount": 1,
        "slotId": 13
    },
    {
        "id": 498,
        "slotName": "Top",
        "name": "Training Tank (Green)",
        "isBasic": false,
        "amount": 1,
        "slotId": 13
    },
    {
        "id": 499,
        "slotName": "Top",
        "name": "Training Tank (Green)",
        "isBasic": false,
        "amount": 1,
        "slotId": 13
    },
    {
        "id": 500,
        "slotName": "Top",
        "name": "Training Tank (Orange)",
        "isBasic": false,
        "amount": 1,
        "slotId": 13
    },
    {
        "id": 501,
        "slotName": "Top",
        "name": "Training Tank (Red)",
        "isBasic": false,
        "amount": 1,
        "slotId": 13
    },
    {
        "id": 502,
        "slotName": "Top",
        "name": "Resistance Armor",
        "isBasic": false,
        "amount": 1,
        "slotId": 13
    },
    {
        "id": 503,
        "slotName": "Top",
        "name": "Shinobi Armor",
        "isBasic": false,
        "amount": 1,
        "slotId": 13
    },
    {
        "id": 504,
        "slotName": "Top",
        "name": "Citrus Top",
        "isBasic": false,
        "amount": 1,
        "slotId": 13
    },
    {
        "id": 505,
        "slotName": "Top",
        "name": "Mandarin Top",
        "isBasic": false,
        "amount": 1,
        "slotId": 13
    },
    {
        "id": 506,
        "slotName": "Top",
        "name": "Consecrated Armor",
        "isBasic": false,
        "amount": 1,
        "slotId": 13
    },
    {
        "id": 507,
        "slotName": "Top",
        "name": "Divine Robe",
        "isBasic": false,
        "amount": 1,
        "slotId": 13
    },
    {
        "id": 508,
        "slotName": "Top",
        "name": "Strange Robe",
        "isBasic": false,
        "amount": 1,
        "slotId": 13
    },
    {
        "id": 509,
        "slotName": "Top",
        "name": "Sniper Tunic",
        "isBasic": false,
        "amount": 1,
        "slotId": 13
    },
    {
        "id": 510,
        "slotName": "Top",
        "name": "Bloodshot Armor",
        "isBasic": false,
        "amount": 1,
        "slotId": 13
    },
    {
        "id": 511,
        "slotName": "Top",
        "name": "Nokizaru Armor",
        "isBasic": false,
        "amount": 1,
        "slotId": 13
    },
    {
        "id": 512,
        "slotName": "Top",
        "name": "Ember Armor",
        "isBasic": false,
        "amount": 1,
        "slotId": 13
    },
    {
        "id": 513,
        "slotName": "Top",
        "name": "Redshirt Shirt",
        "isBasic": false,
        "amount": 1,
        "slotId": 13
    },
    {
        "id": 514,
        "slotName": "Top",
        "name": "Crimson Hakama",
        "isBasic": false,
        "amount": 1,
        "slotId": 13
    },
    {
        "id": 515,
        "slotName": "Top",
        "name": "Assault Armor",
        "isBasic": false,
        "amount": 1,
        "slotId": 13
    },
    {
        "id": 516,
        "slotName": "Top",
        "name": "Crusader Armor",
        "isBasic": false,
        "amount": 1,
        "slotId": 13
    },
    {
        "id": 517,
        "slotName": "Top",
        "name": "Recruit Top",
        "isBasic": false,
        "amount": 1,
        "slotId": 13
    },
    {
        "id": 518,
        "slotName": "Top",
        "name": "Boris Top",
        "isBasic": false,
        "amount": 1,
        "slotId": 13
    },
    {
        "id": 519,
        "slotName": "Top",
        "name": "Marine Armor",
        "isBasic": false,
        "amount": 1,
        "slotId": 13
    },
    {
        "id": 520,
        "slotName": "Top",
        "name": "Gilded Top",
        "isBasic": false,
        "amount": 1,
        "slotId": 13
    },
    {
        "id": 521,
        "slotName": "Top",
        "name": "Lara Top",
        "isBasic": false,
        "amount": 1,
        "slotId": 13
    },
    {
        "id": 522,
        "slotName": "Top",
        "name": "Otaku Jacket",
        "isBasic": false,
        "amount": 1,
        "slotId": 13
    },
    {
        "id": 523,
        "slotName": "Top",
        "name": "Turtleneck Top",
        "isBasic": false,
        "amount": 1,
        "slotId": 13
    },
    {
        "id": 524,
        "slotName": "Top",
        "name": "Penguin Armor",
        "isBasic": false,
        "amount": 1,
        "slotId": 13
    },
    {
        "id": 525,
        "slotName": "Top",
        "name": "The Vest",
        "isBasic": false,
        "amount": 1,
        "slotId": 13
    },
    {
        "id": 526,
        "slotName": "Top",
        "name": "Angel Robes",
        "isBasic": false,
        "amount": 1,
        "slotId": 13
    },
    {
        "id": 527,
        "slotName": "Top",
        "name": "Slayer Armor",
        "isBasic": false,
        "amount": 1,
        "slotId": 13
    },
    {
        "id": 528,
        "slotName": "Top",
        "name": "Celestial Robe",
        "isBasic": false,
        "amount": 1,
        "slotId": 13
    },
    {
        "id": 529,
        "slotName": "Left Hand",
        "name": "Explosive Rain L",
        "isBasic": false,
        "amount": 1,
        "slotId": 10
    },
    {
        "id": 530,
        "slotName": "Class",
        "name": "Gunner",
        "isBasic": true,
        "amount": 1,
        "slotId": 1
    },
    {
        "id": 531,
        "slotName": "Class",
        "name": "Wizard",
        "isBasic": true,
        "amount": 1,
        "slotId": 1
    },
    {
        "id": 532,
        "slotName": "Class",
        "name": "Assassin",
        "isBasic": true,
        "amount": 1,
        "slotId": 1
    },
    {
        "id": 533,
        "slotName": "Class",
        "name": "Tech",
        "isBasic": true,
        "amount": 1,
        "slotId": 1
    },
    {
        "id": 534,
        "slotName": "Class",
        "name": "Knight",
        "isBasic": true,
        "amount": 1,
        "slotId": 1
    },
    {
        "id": 535,
        "slotName": "Gender",
        "name": "Male",
        "isBasic": true,
        "amount": 1,
        "slotId": 6
    },
    {
        "id": 536,
        "slotName": "Gender",
        "name": "Female",
        "isBasic": true,
        "amount": 1,
        "slotId": 6
    }
]